{"annotatable": {"parts": ["title", "abstract"]}, "anncomplete": false, "entities": [{"fields": {}, "offsets": [{"text": "5943 delA", "start": 767}], "normalizations": {}, "confidence": {"who": ["ml:nalaf"], "prob": 1, "state": "selected"}, "part": "abstract", "classId": "e_2"}, {"fields": {}, "offsets": [{"text": "9527 delG", "start": 874}], "normalizations": {}, "confidence": {"who": ["ml:nalaf"], "prob": 1, "state": "selected"}, "part": "abstract", "classId": "e_2"}], "relations": [], "metas": {}, "sources": [{"url": "", "name": "ORIG", "id": "18452888"}]}