{"metas": {}, "entities": [{"fields": {}, "confidence": {"who": ["ml:nalaf"], "prob": 0.784122504682608, "state": "pre-added"}, "normalizations": {}, "part": "s1p2", "classId": "e_2", "offsets": [{"start": 1459, "text": "G88R"}]}, {"fields": {}, "confidence": {"who": ["ml:nalaf"], "prob": 0.6468535211780968, "state": "pre-added"}, "normalizations": {}, "part": "s1p2", "classId": "e_2", "offsets": [{"start": 1465, "text": "I154N"}]}, {"fields": {}, "confidence": {"who": ["ml:nalaf"], "prob": 0.7247207930390999, "state": "pre-added"}, "normalizations": {}, "part": "s1p2", "classId": "e_2", "offsets": [{"start": 1472, "text": "H305R"}]}, {"fields": {}, "confidence": {"who": ["ml:nalaf"], "prob": 0.7845091538416606, "state": "pre-added"}, "normalizations": {}, "part": "s1p2", "classId": "e_2", "offsets": [{"start": 1482, "text": "I352V"}]}, {"fields": {}, "confidence": {"who": ["ml:nalaf"], "prob": 1, "state": "pre-added"}, "normalizations": {}, "part": "s1p2", "classId": "e_2", "offsets": [{"start": 1540, "text": "I154N"}]}, {"fields": {}, "confidence": {"who": ["ml:nalaf"], "prob": 0.5, "state": "pre-added"}, "normalizations": {"n_4": {"recName": "11670"}}, "part": "s1p2", "classId": "e_1", "offsets": [{"start": 1410, "text": "Aldh3a1c"}]}], "anncomplete": false, "relations": [], "annotatable": {"parts": ["s1p1", "s1p2"]}, "sources": [{"name": "ORIG", "id": "10376761", "url": ""}]}