{"annotatable": {"parts": ["title", "abstract"]}, "anncomplete": false, "entities": [{"fields": {}, "offsets": [{"text": "c.115G>A", "start": 455}], "normalizations": {}, "confidence": {"who": ["ml:nalaf"], "prob": 1, "state": "selected"}, "part": "abstract", "classId": "e_2"}, {"fields": {}, "offsets": [{"text": "p.V39M", "start": 465}], "normalizations": {}, "confidence": {"who": ["ml:nalaf"], "prob": 1, "state": "selected"}, "part": "abstract", "classId": "e_2"}, {"fields": {}, "offsets": [{"text": "c.140G>T", "start": 474}], "normalizations": {}, "confidence": {"who": ["ml:nalaf"], "prob": 1, "state": "selected"}, "part": "abstract", "classId": "e_2"}, {"fields": {}, "offsets": [{"text": "p.C47F", "start": 484}], "normalizations": {}, "confidence": {"who": ["ml:nalaf"], "prob": 1, "state": "selected"}, "part": "abstract", "classId": "e_2"}, {"fields": {}, "offsets": [{"text": "c.199T>C", "start": 493}], "normalizations": {}, "confidence": {"who": ["ml:nalaf"], "prob": 1, "state": "selected"}, "part": "abstract", "classId": "e_2"}, {"fields": {}, "offsets": [{"text": "p.S67P", "start": 503}], "normalizations": {}, "confidence": {"who": ["ml:nalaf"], "prob": 1, "state": "selected"}, "part": "abstract", "classId": "e_2"}, {"fields": {}, "offsets": [{"text": "c.278G>T", "start": 512}], "normalizations": {}, "confidence": {"who": ["ml:nalaf"], "prob": 1, "state": "selected"}, "part": "abstract", "classId": "e_2"}, {"fields": {}, "offsets": [{"text": "p.C93F", "start": 522}], "normalizations": {}, "confidence": {"who": ["ml:nalaf"], "prob": 1, "state": "selected"}, "part": "abstract", "classId": "e_2"}, {"fields": {}, "offsets": [{"text": "c.295T>C", "start": 549}], "normalizations": {}, "confidence": {"who": ["ml:nalaf"], "prob": 1, "state": "selected"}, "part": "abstract", "classId": "e_2"}, {"fields": {}, "offsets": [{"text": "p.C99R", "start": 559}], "normalizations": {}, "confidence": {"who": ["ml:nalaf"], "prob": 1, "state": "selected"}, "part": "abstract", "classId": "e_2"}, {"fields": {}, "offsets": [{"text": "p.V39M", "start": 874}], "normalizations": {}, "confidence": {"who": ["ml:nalaf"], "prob": 1, "state": "selected"}, "part": "abstract", "classId": "e_2"}, {"fields": {}, "offsets": [{"text": "p.C47F", "start": 1356}], "normalizations": {}, "confidence": {"who": ["ml:nalaf"], "prob": 1, "state": "selected"}, "part": "abstract", "classId": "e_2"}, {"fields": {}, "offsets": [{"text": "p.C93R", "start": 1364}], "normalizations": {}, "confidence": {"who": ["ml:nalaf"], "prob": 1, "state": "selected"}, "part": "abstract", "classId": "e_2"}, {"fields": {}, "offsets": [{"text": "p.C99R", "start": 1372}], "normalizations": {}, "confidence": {"who": ["ml:nalaf"], "prob": 1, "state": "selected"}, "part": "abstract", "classId": "e_2"}, {"fields": {}, "offsets": [{"text": "p.S67P", "start": 1407}], "normalizations": {}, "confidence": {"who": ["ml:nalaf"], "prob": 1, "state": "selected"}, "part": "abstract", "classId": "e_2"}], "relations": [], "metas": {}, "sources": [{"url": "", "name": "ORIG", "id": "15937921"}]}