{"annotatable": {"parts": ["title", "abstract"]}, "anncomplete": false, "entities": [{"fields": {}, "offsets": [{"text": "c.7872G>A", "start": 825}], "normalizations": {}, "confidence": {"who": ["ml:nalaf"], "prob": 1, "state": "selected"}, "part": "abstract", "classId": "e_2"}, {"fields": {}, "offsets": [{"text": "p.Glu2624Glu", "start": 836}], "normalizations": {}, "confidence": {"who": ["ml:nalaf"], "prob": 1, "state": "selected"}, "part": "abstract", "classId": "e_2"}, {"fields": {}, "offsets": [{"text": "c.2993G>A", "start": 889}], "normalizations": {}, "confidence": {"who": ["ml:nalaf"], "prob": 1, "state": "selected"}, "part": "abstract", "classId": "e_2"}, {"fields": {}, "offsets": [{"text": "p.Arg998Lys", "start": 900}], "normalizations": {}, "confidence": {"who": ["ml:nalaf"], "prob": 1, "state": "selected"}, "part": "abstract", "classId": "e_2"}, {"fields": {}, "offsets": [{"text": "c.592G>A", "start": 923}], "normalizations": {}, "confidence": {"who": ["ml:nalaf"], "prob": 1, "state": "selected"}, "part": "abstract", "classId": "e_2"}, {"fields": {}, "offsets": [{"text": "p.Ala198Thr", "start": 933}], "normalizations": {}, "confidence": {"who": ["ml:nalaf"], "prob": 1, "state": "selected"}, "part": "abstract", "classId": "e_2"}, {"fields": {}, "offsets": [{"text": "c.3503G>C", "start": 947}], "normalizations": {}, "confidence": {"who": ["ml:nalaf"], "prob": 1, "state": "selected"}, "part": "abstract", "classId": "e_2"}, {"fields": {}, "offsets": [{"text": "p.Arg1168Pro", "start": 958}], "normalizations": {}, "confidence": {"who": ["ml:nalaf"], "prob": 1, "state": "selected"}, "part": "abstract", "classId": "e_2"}, {"fields": {}, "offsets": [{"text": "c.5944G>A", "start": 973}], "normalizations": {}, "confidence": {"who": ["ml:nalaf"], "prob": 1, "state": "selected"}, "part": "abstract", "classId": "e_2"}, {"fields": {}, "offsets": [{"text": "p.Gly1982Arg", "start": 984}], "normalizations": {}, "confidence": {"who": ["ml:nalaf"], "prob": 1, "state": "selected"}, "part": "abstract", "classId": "e_2"}, {"fields": {}, "offsets": [{"text": "c.802G>A", "start": 1091}], "normalizations": {}, "confidence": {"who": ["ml:nalaf"], "prob": 1, "state": "selected"}, "part": "abstract", "classId": "e_2"}, {"fields": {}, "offsets": [{"text": "p.Gly268Arg", "start": 1101}], "normalizations": {}, "confidence": {"who": ["ml:nalaf"], "prob": 1, "state": "selected"}, "part": "abstract", "classId": "e_2"}, {"fields": {}, "offsets": [{"text": "c.653T>A", "start": 1115}], "normalizations": {}, "confidence": {"who": ["ml:nalaf"], "prob": 1, "state": "selected"}, "part": "abstract", "classId": "e_2"}, {"fields": {}, "offsets": [{"text": "p.Val218Glu", "start": 1125}], "normalizations": {}, "confidence": {"who": ["ml:nalaf"], "prob": 1, "state": "selected"}, "part": "abstract", "classId": "e_2"}, {"fields": {}, "offsets": [{"text": "c.397C>T", "start": 1151}], "normalizations": {}, "confidence": {"who": ["ml:nalaf"], "prob": 1, "state": "selected"}, "part": "abstract", "classId": "e_2"}, {"fields": {}, "offsets": [{"text": "p.His133Tyr", "start": 1161}], "normalizations": {}, "confidence": {"who": ["ml:nalaf"], "prob": 1, "state": "selected"}, "part": "abstract", "classId": "e_2"}, {"fields": {}, "offsets": [{"text": "c.3502C>T", "start": 1175}], "normalizations": {}, "confidence": {"who": ["ml:nalaf"], "prob": 1, "state": "selected"}, "part": "abstract", "classId": "e_2"}, {"fields": {}, "offsets": [{"text": "p.Arg1168Trp", "start": 1186}], "normalizations": {}, "confidence": {"who": ["ml:nalaf"], "prob": 1, "state": "selected"}, "part": "abstract", "classId": "e_2"}], "relations": [], "metas": {}, "sources": [{"url": "", "name": "ORIG", "id": "20052763"}]}