{"entities": [{"classId": "e_1", "part": "s1p1", "confidence": {"who": ["ml:nalaf"], "state": "", "prob": 0.5}, "offsets": [{"text": "ABC1", "start": 20}], "normalizations": {"n_4": {"recName": "19"}}, "fields": {}}, {"classId": "e_2", "part": "s1p2", "confidence": {"who": ["ml:nalaf"], "state": "", "prob": 1}, "offsets": [{"text": "C>T transition in exon 13", "start": 1165}], "normalizations": {}, "fields": {}}, {"classId": "e_2", "part": "s1p2", "confidence": {"who": ["ml:nalaf"], "state": "", "prob": 1}, "offsets": [{"text": "which caused a tryptophane for arginine", "start": 1192}], "normalizations": {}, "fields": {}}, {"classId": "e_2", "part": "s1p2", "confidence": {"who": ["ml:nalaf"], "state": "", "prob": 0.9939372458440072}, "offsets": [{"text": "R527W", "start": 1246}], "normalizations": {}, "fields": {}}, {"classId": "e_2", "part": "s1p2", "confidence": {"who": ["ml:nalaf"], "state": "", "prob": 0.9697396419262994}, "offsets": [{"text": "R527W", "start": 1448}], "normalizations": {}, "fields": {}}, {"classId": "e_1", "part": "s1p2", "confidence": {"who": ["ml:nalaf"], "state": "", "prob": 0.5}, "offsets": [{"text": "ABC1", "start": 1536}], "normalizations": {"n_4": {"recName": "19"}}, "fields": {}}, {"classId": "e_2", "part": "s1p2", "confidence": {"who": ["ml:nalaf"], "state": "", "prob": 0.8604336375575871}, "offsets": [{"text": "R527W", "start": 1550}], "normalizations": {}, "fields": {}}], "anncomplete": true, "metas": {}, "relations": [], "annotatable": {"parts": ["s1p1", "s1p2"]}, "sources": [{"name": "ORIG", "url": "", "id": "11257260"}, {"name": "PMID", "url": "http://www.ncbi.nlm.nih.gov/pubmed/11257260", "id": "11257260"}]}