{"sources": [{"id": "19129715", "url": "", "name": "ORIG"}], "anncomplete": false, "entities": [{"fields": {}, "normalizations": {"n_4": {"recName": "3483"}}, "offsets": [{"start": 12, "text": "IGFALS"}], "part": "title", "confidence": {"who": ["ml:nalaf"], "state": "pre-added", "prob": 0.5}, "classId": "e_1"}, {"fields": {}, "normalizations": {"n_4": {"recName": "3479"}}, "offsets": [{"start": 80, "text": "IGF-I"}], "part": "title", "confidence": {"who": ["ml:nalaf"], "state": "pre-added", "prob": 0.5}, "classId": "e_1"}, {"fields": {}, "normalizations": {"n_4": {"recName": "3486"}}, "offsets": [{"start": 86, "text": "IGFBP-3"}], "part": "title", "confidence": {"who": ["ml:nalaf"], "state": "pre-added", "prob": 0.5}, "classId": "e_1"}, {"fields": {}, "normalizations": {}, "offsets": [{"start": 927, "text": "C60S"}], "part": "abstract", "confidence": {"who": ["ml:nalaf"], "state": "pre-added", "prob": 0.7943968496357029}, "classId": "e_2"}, {"fields": {}, "normalizations": {}, "offsets": [{"start": 932, "text": "L244F"}], "part": "abstract", "confidence": {"who": ["ml:nalaf"], "state": "pre-added", "prob": 0.9163355155832207}, "classId": "e_2"}, {"fields": {}, "normalizations": {"n_4": {"recName": "3483"}}, "offsets": [{"start": 48, "text": "IGFALS"}], "part": "abstract", "confidence": {"who": ["ml:nalaf"], "state": "pre-added", "prob": 0.5}, "classId": "e_1"}, {"fields": {}, "normalizations": {"n_4": {"recName": "3479"}}, "offsets": [{"start": 200, "text": "IGF-I"}], "part": "abstract", "confidence": {"who": ["ml:nalaf"], "state": "pre-added", "prob": 0.5}, "classId": "e_1"}, {"fields": {}, "normalizations": {"n_4": {"recName": "3486"}}, "offsets": [{"start": 206, "text": "IGFBP-3"}], "part": "abstract", "confidence": {"who": ["ml:nalaf"], "state": "pre-added", "prob": 0.5}, "classId": "e_1"}, {"fields": {}, "normalizations": {"n_4": {"recName": "3483"}}, "offsets": [{"start": 271, "text": "IGFALS"}], "part": "abstract", "confidence": {"who": ["ml:nalaf"], "state": "pre-added", "prob": 0.5}, "classId": "e_1"}, {"fields": {}, "normalizations": {"n_4": {"recName": "3479"}}, "offsets": [{"start": 686, "text": "IGF-I"}], "part": "abstract", "confidence": {"who": ["ml:nalaf"], "state": "pre-added", "prob": 0.5}, "classId": "e_1"}, {"fields": {}, "normalizations": {"n_4": {"recName": "3486"}}, "offsets": [{"start": 696, "text": "IGFBP-3"}], "part": "abstract", "confidence": {"who": ["ml:nalaf"], "state": "pre-added", "prob": 0.5}, "classId": "e_1"}, {"fields": {}, "normalizations": {"n_4": {"recName": "122769"}}, "offsets": [{"start": 992, "text": "LRR 1"}], "part": "abstract", "confidence": {"who": ["ml:nalaf"], "state": "pre-added", "prob": 0.5}, "classId": "e_1"}, {"fields": {}, "normalizations": {"n_4": {"recName": "3483"}}, "offsets": [{"start": 1075, "text": "IGFALS"}], "part": "abstract", "confidence": {"who": ["ml:nalaf"], "state": "pre-added", "prob": 0.5}, "classId": "e_1"}, {"fields": {}, "normalizations": {"n_4": {"recName": "3479"}}, "offsets": [{"start": 1113, "text": "IGF-I"}], "part": "abstract", "confidence": {"who": ["ml:nalaf"], "state": "pre-added", "prob": 0.5}, "classId": "e_1"}, {"fields": {}, "normalizations": {"n_4": {"recName": "3486"}}, "offsets": [{"start": 1119, "text": "IGFBP-3"}], "part": "abstract", "confidence": {"who": ["ml:nalaf"], "state": "pre-added", "prob": 0.5}, "classId": "e_1"}, {"fields": {}, "normalizations": {"n_4": {"recName": "3483"}}, "offsets": [{"start": 1158, "text": "IGFALS"}], "part": "abstract", "confidence": {"who": ["ml:nalaf"], "state": "pre-added", "prob": 0.5}, "classId": "e_1"}], "relations": [], "annotatable": {"parts": ["title", "abstract"]}, "metas": {}}