{"anncomplete":false,"sources":[{"name":"ORIG","id":"PMC2267738","url":"http://www.ncbi.nlm.nih.gov/pmc/articles/PMC2267738/"},{"name":"PMID","id":"18246032","url":"http://www.ncbi.nlm.nih.gov/pubmed/18246032"}],"entities":[{"classId":"e_2","part":"s2s3p1","offsets":[{"start":259,"text":"conservative substitution of Cys to Phe at codon 271 (p.C271F)"}],"confidence":{"state":"","who":["user:cuhlig"],"prob":1},"fields":{},"normalizations":{}},{"classId":"e_2","part":"s5s3p1","offsets":[{"start":81,"text":"conservative substitution of Cys to Phe at codon 271 (p.C271F)"}],"confidence":{"state":"pre-added","who":["user:cuhlig"],"prob":1},"fields":{},"normalizations":{}},{"classId":"e_2","part":"s5s3f1p1","offsets":[{"start":262,"text":"conservative substitution of Cys to Phe at codon 271 (p.C271F)"}],"confidence":{"state":"pre-added","who":["user:cuhlig"],"prob":1},"fields":{},"normalizations":{}}],"relations":[],"metas":{},"annotatable":{"parts":["s1h1","s2h1","s2s1h1","s2s1p1","s2s2h1","s2s2p1","s2s3h1","s2s3p1","s2s4h1","s2s4p1","s3h1","s3p1","s3p2","s3p3","s3p4","s3f1p1","s4h1","s4s1h1","s4s1p1","s4s1f1p1","s4s2h1","s4s2p1","s4s3h1","s4s3p1","s4s4h1","s4s4p1","s4s5h1","s4s5p1","s5h1","s5s1h1","s5s1p1","s5s1p2","s5s2h1","s5s2p1","s5s3h1","s5s3p1","s5s3f1p1","s5s4h1","s5s4p1","s5s4p2","s5s4p3","s5s5h1","s5s5p1","s6h1","s6p1","s6p2","s6p3","s6p4","s6p5","s6p6","s6p7","s6p8","s6p9","s6p10","s6p11"]}}