{"annotatable": {"parts": ["s1p1", "s1p2"]}, "relations": [], "entities": [{"confidence": {"state": "", "who": ["user:cuhlig"], "prob": 1}, "part": "s1p2", "normalizations": {}, "fields": {}, "classId": "e_1", "offsets": [{"start": 31, "text": "ACE"}]}, {"confidence": {"state": "", "who": ["user:cuhlig"], "prob": 1}, "part": "s1p2", "normalizations": {}, "fields": {}, "classId": "e_1", "offsets": [{"start": 363, "text": "ACE"}]}, {"confidence": {"state": "", "who": ["ml:nalaf"], "prob": 0.9733901234416644}, "part": "s1p2", "normalizations": {}, "fields": {}, "classId": "e_2", "offsets": [{"start": 436, "text": "Pro(1199) --> Leu"}]}, {"confidence": {"state": "", "who": ["user:cuhlig"], "prob": 1}, "part": "s1p2", "normalizations": {}, "fields": {}, "classId": "e_1", "offsets": [{"start": 557, "text": "ACE"}]}, {"confidence": {"state": "", "who": ["user:cuhlig"], "prob": 1}, "part": "s1p2", "normalizations": {}, "fields": {}, "classId": "e_1", "offsets": [{"start": 598, "text": "ACE"}]}, {"confidence": {"state": "", "who": ["user:cuhlig"], "prob": 1}, "part": "s1p2", "normalizations": {}, "fields": {}, "classId": "e_1", "offsets": [{"start": 644, "text": "ACE"}]}, {"confidence": {"state": "", "who": ["user:cuhlig"], "prob": 1}, "part": "s1p2", "normalizations": {}, "fields": {}, "classId": "e_1", "offsets": [{"start": 726, "text": "ACE"}]}, {"confidence": {"state": "", "who": ["user:cuhlig"], "prob": 1}, "part": "s1p2", "normalizations": {}, "fields": {}, "classId": "e_1", "offsets": [{"start": 900, "text": "ACE"}]}, {"confidence": {"state": "", "who": ["ml:nalaf"], "prob": 0.9827954330921129}, "part": "s1p2", "normalizations": {}, "fields": {}, "classId": "e_2", "offsets": [{"start": 1094, "text": "Pro(1199) --> Leu"}]}, {"confidence": {"state": "", "who": ["user:cuhlig"], "prob": 1}, "part": "s1p2", "normalizations": {}, "fields": {}, "classId": "e_1", "offsets": [{"start": 1173, "text": "ACE"}]}, {"confidence": {"state": "", "who": ["user:cuhlig"], "prob": 1}, "part": "s1p2", "normalizations": {}, "fields": {}, "classId": "e_1", "offsets": [{"start": 1373, "text": "ACE"}]}], "anncomplete": true, "sources": [{"name": "ORIG", "id": "11076943", "url": ""}, {"name": "PMID", "id": "11076943", "url": "http://www.ncbi.nlm.nih.gov/pubmed/11076943"}], "metas": {}}