{"sources": [{"id": "10477429", "url": "", "name": "ORIG"}], "metas": {}, "annotatable": {"parts": ["title", "abstract"]}, "entities": [{"confidence": {"prob": 0.8943855415110087, "state": "", "who": ["ml:nalaf"]}, "offsets": [{"start": 301, "text": "TP53 gene at codon 133 (ATG--> ACG"}], "classId": "e_2", "fields": {}, "normalizations": {}, "part": "abstract"}, {"confidence": {"prob": 0.8327894103708472, "state": "", "who": ["ml:nalaf"]}, "offsets": [{"start": 337, "text": "M133T"}], "classId": "e_2", "fields": {}, "normalizations": {}, "part": "abstract"}], "anncomplete": false, "relations": []}