{"sources": [{"id": "10486328", "url": "", "name": "ORIG"}], "metas": {}, "annotatable": {"parts": ["title", "abstract"]}, "entities": [{"confidence": {"prob": 0.7046436284773473, "state": "", "who": ["ml:nalaf"]}, "offsets": [{"start": 731, "text": "D11S4144"}], "classId": "e_2", "fields": {}, "normalizations": {}, "part": "abstract"}, {"confidence": {"prob": 0.6357426880885275, "state": "", "who": ["ml:nalaf"]}, "offsets": [{"start": 744, "text": "D11S1351"}], "classId": "e_2", "fields": {}, "normalizations": {}, "part": "abstract"}, {"confidence": {"prob": 0.7858774431971574, "state": "", "who": ["ml:nalaf"]}, "offsets": [{"start": 926, "text": "D11S933"}], "classId": "e_2", "fields": {}, "normalizations": {}, "part": "abstract"}, {"confidence": {"prob": 0.8450956510341943, "state": "", "who": ["ml:nalaf"]}, "offsets": [{"start": 938, "text": "D11S934"}], "classId": "e_2", "fields": {}, "normalizations": {}, "part": "abstract"}], "anncomplete": false, "relations": []}