{"sources": [{"id": "17285591", "url": "", "name": "ORIG"}], "metas": {}, "annotatable": {"parts": ["title", "abstract"]}, "entities": [{"confidence": {"prob": 0.5798019401707237, "state": "", "who": ["ml:nalaf"]}, "offsets": [{"start": 843, "text": "sY1191"}], "classId": "e_2", "fields": {}, "normalizations": {}, "part": "abstract"}, {"confidence": {"prob": 0.6044405416704722, "state": "", "who": ["ml:nalaf"]}, "offsets": [{"start": 1497, "text": "AZFc partial deletion"}], "classId": "e_2", "fields": {}, "normalizations": {}, "part": "abstract"}], "anncomplete": false, "relations": []}