{"anncomplete": false, "entities": [{"part": "abstract", "normalizations": {}, "confidence": {"state": "", "who": ["ml:nalaf"], "prob": 0.8459629964823894}, "classId": "e_2", "offsets": [{"text": "c.385G", "start": 120}], "fields": {}}, {"part": "abstract", "normalizations": {}, "confidence": {"state": "", "who": ["ml:nalaf"], "prob": 0.9539266821225123}, "classId": "e_2", "offsets": [{"text": "cysteine at codon 129", "start": 214}], "fields": {}}, {"part": "abstract", "normalizations": {}, "confidence": {"state": "", "who": ["ml:nalaf"], "prob": 0.9871723171540102}, "classId": "e_2", "offsets": [{"text": "p.Gly129Cys", "start": 237}], "fields": {}}, {"part": "abstract", "normalizations": {}, "confidence": {"state": "", "who": ["ml:nalaf"], "prob": 0.9684518138443508}, "classId": "e_2", "offsets": [{"text": "p.Gly129Cys", "start": 433}], "fields": {}}, {"part": "abstract", "normalizations": {}, "confidence": {"state": "", "who": ["ml:nalaf"], "prob": 0.9793294722606207}, "classId": "e_2", "offsets": [{"text": "p.Gly129Cys", "start": 1041}], "fields": {}}], "metas": {}, "sources": [{"name": "ORIG", "id": "22052681", "url": ""}], "relations": [], "annotatable": {"parts": ["title", "abstract"]}}