{"sources": [{"id": "22405088", "url": "", "name": "ORIG"}], "metas": {}, "annotatable": {"parts": ["title", "abstract"]}, "entities": [{"confidence": {"prob": 0.9930438571414475, "state": "", "who": ["ml:nalaf"]}, "offsets": [{"start": 327, "text": "p.Gly573Ser"}], "classId": "e_2", "fields": {}, "normalizations": {}, "part": "abstract"}, {"confidence": {"prob": 0.9956479875035651, "state": "", "who": ["ml:nalaf"]}, "offsets": [{"start": 485, "text": "p.Gly573Ser"}], "classId": "e_2", "fields": {}, "normalizations": {}, "part": "abstract"}, {"confidence": {"prob": 0.9989970634619741, "state": "", "who": ["ml:nalaf"]}, "offsets": [{"start": 516, "text": "p.Gly573Cys"}], "classId": "e_2", "fields": {}, "normalizations": {}, "part": "abstract"}, {"confidence": {"prob": 0.9963047190091199, "state": "", "who": ["ml:nalaf"]}, "offsets": [{"start": 532, "text": "p.Trp692Gly"}], "classId": "e_2", "fields": {}, "normalizations": {}, "part": "abstract"}], "anncomplete": false, "relations": []}